<?xml version="1.0" encoding="UTF-8"?>
<launch4jConfig>
  <dontWrapJar>false</dontWrapJar>
  <headerType>gui</headerType>
  <jar>C:\Mika4Softwares\SheetHelperEvo\SheetHelperEvo.jar</jar>
  <outfile>SheetHelperEvo.exe</outfile>
  <errTitle></errTitle>
  <cmdLine></cmdLine>
  <chdir>.</chdir>
  <priority>normal</priority>
  <downloadUrl></downloadUrl>
  <supportUrl></supportUrl>
  <stayAlive>false</stayAlive>
  <restartOnCrash>false</restartOnCrash>
  <manifest></manifest>
  <icon>C:\Mika4Softwares\SheetHelperEvo\SheetHelper.ico</icon>
  <jre>
    <path>%JAVA_HOME%;%PATH%</path>
    <requiresJdk>false</requiresJdk>
    <requires64Bit>false</requires64Bit>
    <minVersion>1.0.0</minVersion>
    <maxVersion>1.8.0</maxVersion>
  </jre>
</launch4jConfig>